{
  "$schema": "https://developer.microsoft.com/json-schemas/fabric/item/report/definition/visualContainer/1.4.0/schema.json",
  "name": "039fd6f9d3bb78c9f589",
  "position": {
    "x": 0,
    "y": 0,
    "z": 1002,
    "height": 360.27346741936395,
    "width": 625.23048991517965,
    "tabOrder": 1002
  },
  "visual": {
    "visualType": "image",
    "objects": {
      "general": [
        {
          "properties": {
            "imageUrl": {
              "expr": {
                "ResourcePackageItem": {
                  "PackageName": "RegisteredResources",
                  "PackageType": 1,
                  "ItemName": "TP_1_2_-13063152204339905.png"
                }
              }
            }
          }
        }
      ]
    },
    "drillFilterOtherVisuals": true
  },
  "howCreated": "InsertVisualButton"
}