{
  "$schema": "https://developer.microsoft.com/json-schemas/fabric/item/report/definition/visualContainer/1.4.0/schema.json",
  "name": "65a947ede79bbe465702",
  "position": {
    "x": 275.60937071888634,
    "y": 127.35164404179764,
    "z": 3000,
    "height": 38.571428571428577,
    "width": 172.85714285714286,
    "tabOrder": 2000
  },
  "visual": {
    "visualType": "textbox",
    "objects": {
      "general": [
        {
          "properties": {
            "paragraphs": [
              {
                "textRuns": [
                  {
                    "value": "Résultat du bouclage",
                    "textStyle": {
                      "fontWeight": "bold",
                      "fontFamily": "DIN",
                      "fontSize": "8pt",
                      "color": "#000000"
                    }
                  }
                ]
              }
            ]
          }
        }
      ]
    },
    "visualContainerObjects": {
      "visualHeader": [
        {
          "properties": {
            "show": {
              "expr": {
                "Literal": {
                  "Value": "false"
                }
              }
            }
          }
        }
      ]
    },
    "drillFilterOtherVisuals": true
  }
}