{
  "$schema": "https://developer.microsoft.com/json-schemas/fabric/item/report/definition/visualContainer/1.4.0/schema.json",
  "name": "f56c6c247a68a443da39",
  "position": {
    "x": 250.79096045197741,
    "y": 123.44632768361582,
    "z": 6000,
    "height": 316,
    "width": 585.39548022598865,
    "tabOrder": 2000
  },
  "visual": {
    "visualType": "pivotTable",
    "query": {
      "queryState": {
        "Rows": {
          "projections": [
            {
              "field": {
                "Column": {
                  "Expression": {
                    "SourceRef": {
                      "Entity": "PlanCompteAEF"
                    }
                  },
                  "Property": "CategorieBFR"
                }
              },
              "queryRef": "PlanCompteAEF.CategorieBFR",
              "nativeQueryRef": "‎ ",
              "active": true,
              "displayName": "‎ "
            },
            {
              "field": {
                "Column": {
                  "Expression": {
                    "SourceRef": {
                      "Entity": "PlanCompteAEF"
                    }
                  },
                  "Property": "SousCategorieBFR"
                }
              },
              "queryRef": "PlanCompteAEF.SousCategorieBFR",
              "nativeQueryRef": "SousCategorieBFR",
              "active": true
            },
            {
              "field": {
                "Column": {
                  "Expression": {
                    "SourceRef": {
                      "Entity": "PlanCompteAEF"
                    }
                  },
                  "Property": "LiasseLibelleAffichage"
                }
              },
              "queryRef": "PlanCompteAEF.LiasseLibelleAffichage",
              "nativeQueryRef": "LiasseLibelleAffichage",
              "active": false
            },
            {
              "field": {
                "Column": {
                  "Expression": {
                    "SourceRef": {
                      "Entity": "KPI"
                    }
                  },
                  "Property": "CompteName"
                }
              },
              "queryRef": "KPI.CompteName",
              "nativeQueryRef": "CompteName",
              "active": false
            }
          ],
          "showAll": true
        },
        "Values": {
          "projections": [
            {
              "field": {
                "Measure": {
                  "Expression": {
                    "SourceRef": {
                      "Entity": "KPI"
                    }
                  },
                  "Property": "_Solde table KPI N cumulé"
                }
              },
              "queryRef": "KPI._Solde table KPI N cumulé",
              "nativeQueryRef": "Solde N 1",
              "displayName": "Solde N"
            },
            {
              "field": {
                "Measure": {
                  "Expression": {
                    "SourceRef": {
                      "Entity": "KPI"
                    }
                  },
                  "Property": "_Solde table KPI N-1 cumulé"
                }
              },
              "queryRef": "KPI._Solde table KPI N-1 cumulé",
              "nativeQueryRef": "Solde N-1 1",
              "displayName": "Solde N-1"
            },
            {
              "field": {
                "Measure": {
                  "Expression": {
                    "SourceRef": {
                      "Entity": "KPI"
                    }
                  },
                  "Property": "_variation table KPI cumulé"
                }
              },
              "queryRef": "KPI._variation table KPI cumulé",
              "nativeQueryRef": "Variation 1",
              "displayName": "Variation"
            },
            {
              "field": {
                "Measure": {
                  "Expression": {
                    "SourceRef": {
                      "Entity": "KPI"
                    }
                  },
                  "Property": "_variation table KPI cumulé %"
                }
              },
              "queryRef": "KPI._variation table KPI cumulé %",
              "nativeQueryRef": "% 1",
              "displayName": "%"
            }
          ]
        }
      },
      "sortDefinition": {
        "sort": [
          {
            "field": {
              "Column": {
                "Expression": {
                  "SourceRef": {
                    "Entity": "PlanCompteAEF"
                  }
                },
                "Property": "CategorieBFR"
              }
            },
            "direction": "Ascending"
          },
          {
            "field": {
              "Column": {
                "Expression": {
                  "SourceRef": {
                    "Entity": "PlanCompteAEF"
                  }
                },
                "Property": "SousCategorieBFR"
              }
            },
            "direction": "Ascending"
          }
        ]
      }
    },
    "expansionStates": [
      {
        "roles": [
          "Rows"
        ],
        "levels": [
          {
            "queryRefs": [
              "PlanCompteAEF.CategorieBFR"
            ],
            "isCollapsed": true,
            "identityKeys": [
              {
                "Column": {
                  "Expression": {
                    "SourceRef": {
                      "Entity": "PlanCompteAEF"
                    }
                  },
                  "Property": "CategorieBFR"
                }
              }
            ],
            "isPinned": true
          },
          {
            "queryRefs": [
              "PlanCompteAEF.SousCategorieBFR"
            ],
            "isCollapsed": true,
            "isPinned": true
          },
          {
            "queryRefs": [
              "PlanCompteAEF.LiasseLibelleAffichage"
            ],
            "isCollapsed": true
          },
          {
            "queryRefs": [
              "KPI.CompteName"
            ],
            "isCollapsed": true
          }
        ],
        "root": {
          "children": [
            {
              "identityValues": [
                {
                  "Literal": {
                    "Value": "'BFR d''exploitation'"
                  }
                }
              ],
              "isToggled": true
            },
            {
              "identityValues": [
                {
                  "Literal": {
                    "Value": "'BFR hors exploitation'"
                  }
                }
              ],
              "isToggled": true
            }
          ]
        }
      }
    ],
    "objects": {
      "columnHeaders": [
        {
          "properties": {
            "fontColor": {
              "solid": {
                "color": {
                  "expr": {
                    "ThemeDataColor": {
                      "ColorId": 7,
                      "Percent": 0
                    }
                  }
                }
              }
            },
            "fontFamily": {
              "expr": {
                "Literal": {
                  "Value": "'wf_standard-font, helvetica, arial, sans-serif'"
                }
              }
            },
            "fontSize": {
              "expr": {
                "Literal": {
                  "Value": "8D"
                }
              }
            },
            "backColor": {
              "solid": {
                "color": {
                  "expr": {
                    "ThemeDataColor": {
                      "ColorId": 2,
                      "Percent": 0
                    }
                  }
                }
              }
            },
            "alignment": {
              "expr": {
                "Literal": {
                  "Value": "'center'"
                }
              }
            },
            "wordWrap": {
              "expr": {
                "Literal": {
                  "Value": "false"
                }
              }
            },
            "bold": {
              "expr": {
                "Literal": {
                  "Value": "true"
                }
              }
            }
          }
        }
      ],
      "grid": [
        {
          "properties": {
            "outlineColor": {
              "solid": {
                "color": {
                  "expr": {
                    "ThemeDataColor": {
                      "ColorId": 3,
                      "Percent": 0
                    }
                  }
                }
              }
            },
            "outlineWeight": {
              "expr": {
                "Literal": {
                  "Value": "1D"
                }
              }
            },
            "rowPadding": {
              "expr": {
                "Literal": {
                  "Value": "3L"
                }
              }
            }
          }
        }
      ],
      "rowHeaders": [
        {
          "properties": {
            "fontColor": {
              "solid": {
                "color": {
                  "expr": {
                    "ThemeDataColor": {
                      "ColorId": 1,
                      "Percent": 0
                    }
                  }
                }
              }
            },
            "fontFamily": {
              "expr": {
                "Literal": {
                  "Value": "'wf_standard-font, helvetica, arial, sans-serif'"
                }
              }
            },
            "fontSize": {
              "expr": {
                "Literal": {
                  "Value": "8D"
                }
              }
            },
            "wordWrap": {
              "expr": {
                "Literal": {
                  "Value": "false"
                }
              }
            },
            "expandCollapseButtonsColor": {
              "solid": {
                "color": {
                  "expr": {
                    "ThemeDataColor": {
                      "ColorId": 8,
                      "Percent": 0
                    }
                  }
                }
              }
            }
          }
        }
      ],
      "values": [
        {
          "properties": {
            "fontFamily": {
              "expr": {
                "Literal": {
                  "Value": "'wf_standard-font, helvetica, arial, sans-serif'"
                }
              }
            },
            "fontSize": {
              "expr": {
                "Literal": {
                  "Value": "8D"
                }
              }
            },
            "wordWrap": {
              "expr": {
                "Literal": {
                  "Value": "false"
                }
              }
            },
            "valuesOnRow": {
              "expr": {
                "Literal": {
                  "Value": "false"
                }
              }
            }
          }
        }
      ],
      "subTotals": [
        {
          "properties": {
            "rowSubtotalsLabel": {
              "expr": {
                "Literal": {
                  "Value": "'Besoin en Fonds de Roulement'"
                }
              }
            }
          }
        },
        {
          "properties": {
            "bold": {
              "expr": {
                "Literal": {
                  "Value": "true"
                }
              }
            },
            "backColor": {
              "solid": {
                "color": {
                  "expr": {
                    "ThemeDataColor": {
                      "ColorId": 0,
                      "Percent": 0
                    }
                  }
                }
              }
            },
            "applyToHeaders": {
              "expr": {
                "Literal": {
                  "Value": "true"
                }
              }
            }
          },
          "selector": {
            "id": "Row"
          }
        },
        {
          "properties": {
            "levelSubtotalEnabled": {
              "expr": {
                "Literal": {
                  "Value": "true"
                }
              }
            }
          },
          "selector": {
            "metadata": "PlanCompteAEF.CategorieEndettementNet"
          }
        },
        {
          "properties": {
            "levelSubtotalEnabled": {
              "expr": {
                "Literal": {
                  "Value": "true"
                }
              }
            }
          },
          "selector": {
            "metadata": "PlanCompteAEF.LiasseLibelleAffichage"
          }
        }
      ],
      "columnFormatting": [
        {
          "properties": {
            "dataBars": {
              "positiveColor": {
                "solid": {
                  "color": {
                    "expr": {
                      "Literal": {
                        "Value": "'#FEA19E'"
                      }
                    }
                  }
                }
              },
              "negativeColor": {
                "solid": {
                  "color": {
                    "expr": {
                      "Literal": {
                        "Value": "'#A4E38A'"
                      }
                    }
                  }
                }
              },
              "axisColor": {
                "solid": {
                  "color": {
                    "expr": {
                      "Literal": {
                        "Value": "'#FFFFFF'"
                      }
                    }
                  }
                }
              },
              "reverseDirection": {
                "expr": {
                  "Literal": {
                    "Value": "false"
                  }
                }
              },
              "hideText": {
                "expr": {
                  "Literal": {
                    "Value": "false"
                  }
                }
              },
              "totalMatchingOption": {
                "expr": {
                  "Literal": {
                    "Value": "1L"
                  }
                }
              }
            },
            "styleHeader": {
              "expr": {
                "Literal": {
                  "Value": "true"
                }
              }
            },
            "styleSubtotals": {
              "expr": {
                "Literal": {
                  "Value": "false"
                }
              }
            },
            "styleValues": {
              "expr": {
                "Literal": {
                  "Value": "false"
                }
              }
            },
            "alignment": {
              "expr": {
                "Literal": {
                  "Value": "'Center'"
                }
              }
            }
          },
          "selector": {
            "metadata": "KPI._variation table KPI cumulé"
          }
        },
        {
          "properties": {},
          "selector": {
            "metadata": "PlanCompteAEF.CategorieBFR"
          }
        },
        {
          "properties": {
            "styleHeader": {
              "expr": {
                "Literal": {
                  "Value": "true"
                }
              }
            },
            "styleSubtotals": {
              "expr": {
                "Literal": {
                  "Value": "false"
                }
              }
            },
            "styleValues": {
              "expr": {
                "Literal": {
                  "Value": "false"
                }
              }
            },
            "alignment": {
              "expr": {
                "Literal": {
                  "Value": "'Center'"
                }
              }
            }
          },
          "selector": {
            "metadata": "KPI._Solde table KPI N cumulé"
          }
        },
        {
          "properties": {
            "styleHeader": {
              "expr": {
                "Literal": {
                  "Value": "true"
                }
              }
            },
            "styleSubtotals": {
              "expr": {
                "Literal": {
                  "Value": "false"
                }
              }
            },
            "styleValues": {
              "expr": {
                "Literal": {
                  "Value": "false"
                }
              }
            },
            "alignment": {
              "expr": {
                "Literal": {
                  "Value": "'Center'"
                }
              }
            }
          },
          "selector": {
            "metadata": "KPI._Solde table KPI N-1 cumulé"
          }
        },
        {
          "properties": {
            "styleHeader": {
              "expr": {
                "Literal": {
                  "Value": "true"
                }
              }
            },
            "styleSubtotals": {
              "expr": {
                "Literal": {
                  "Value": "false"
                }
              }
            },
            "styleValues": {
              "expr": {
                "Literal": {
                  "Value": "false"
                }
              }
            },
            "alignment": {
              "expr": {
                "Literal": {
                  "Value": "'Center'"
                }
              }
            }
          },
          "selector": {
            "metadata": "KPI._variation table KPI cumulé %"
          }
        },
        {
          "properties": {
            "alignment": {
              "expr": {
                "Literal": {
                  "Value": "'Center'"
                }
              }
            },
            "styleHeader": {
              "expr": {
                "Literal": {
                  "Value": "true"
                }
              }
            },
            "styleValues": {
              "expr": {
                "Literal": {
                  "Value": "false"
                }
              }
            },
            "styleSubtotals": {
              "expr": {
                "Literal": {
                  "Value": "false"
                }
              }
            }
          },
          "selector": {
            "metadata": "KPI._Gene_Variation N/N-1"
          }
        },
        {
          "properties": {
            "alignment": {
              "expr": {
                "Literal": {
                  "Value": "'Center'"
                }
              }
            },
            "styleHeader": {
              "expr": {
                "Literal": {
                  "Value": "true"
                }
              }
            },
            "styleValues": {
              "expr": {
                "Literal": {
                  "Value": "false"
                }
              }
            },
            "styleSubtotals": {
              "expr": {
                "Literal": {
                  "Value": "false"
                }
              }
            }
          },
          "selector": {
            "metadata": "KPI._Gene_Solde N"
          }
        },
        {
          "properties": {
            "alignment": {
              "expr": {
                "Literal": {
                  "Value": "'Center'"
                }
              }
            },
            "styleHeader": {
              "expr": {
                "Literal": {
                  "Value": "true"
                }
              }
            },
            "styleValues": {
              "expr": {
                "Literal": {
                  "Value": "false"
                }
              }
            },
            "styleSubtotals": {
              "expr": {
                "Literal": {
                  "Value": "false"
                }
              }
            }
          },
          "selector": {
            "metadata": "KPI._Gene_Solde N-1"
          }
        },
        {
          "properties": {
            "alignment": {
              "expr": {
                "Literal": {
                  "Value": "'Center'"
                }
              }
            },
            "styleHeader": {
              "expr": {
                "Literal": {
                  "Value": "true"
                }
              }
            },
            "styleValues": {
              "expr": {
                "Literal": {
                  "Value": "false"
                }
              }
            },
            "styleSubtotals": {
              "expr": {
                "Literal": {
                  "Value": "false"
                }
              }
            }
          },
          "selector": {
            "metadata": "KPI._Gene_VariationN/N-1%"
          }
        },
        {
          "properties": {
            "alignment": {
              "expr": {
                "Literal": {
                  "Value": "'Center'"
                }
              }
            },
            "styleHeader": {
              "expr": {
                "Literal": {
                  "Value": "true"
                }
              }
            },
            "styleValues": {
              "expr": {
                "Literal": {
                  "Value": "false"
                }
              }
            },
            "styleSubtotals": {
              "expr": {
                "Literal": {
                  "Value": "false"
                }
              }
            }
          },
          "selector": {
            "metadata": "KPI.Solde TFT Vecrit."
          }
        }
      ],
      "columnWidth": [
        {
          "properties": {
            "value": {
              "expr": {
                "Literal": {
                  "Value": "235.37853134807966D"
                }
              }
            }
          },
          "selector": {
            "metadata": "PlanCompteAEF.CategorieEndettementNet"
          }
        },
        {
          "properties": {
            "value": {
              "expr": {
                "Literal": {
                  "Value": "93.23729238891006D"
                }
              }
            }
          },
          "selector": {
            "metadata": "KPI._Gene_Solde N"
          }
        },
        {
          "properties": {
            "value": {
              "expr": {
                "Literal": {
                  "Value": "82.03954073347815D"
                }
              }
            }
          },
          "selector": {
            "metadata": "KPI._Gene_Solde N-1"
          }
        },
        {
          "properties": {
            "value": {
              "expr": {
                "Literal": {
                  "Value": "80.44067320423979D"
                }
              }
            }
          },
          "selector": {
            "metadata": "KPI._Gene_Variation N/N-1"
          }
        },
        {
          "properties": {
            "value": {
              "expr": {
                "Literal": {
                  "Value": "62.440711867685465D"
                }
              }
            }
          },
          "selector": {
            "metadata": "KPI._Gene_VariationN/N-1%"
          }
        },
        {
          "properties": {
            "value": {
              "expr": {
                "Literal": {
                  "Value": "152D"
                }
              }
            }
          },
          "selector": {
            "data": [
              {
                "scopeId": {
                  "Comparison": {
                    "ComparisonKind": 0,
                    "Left": {
                      "Column": {
                        "Expression": {
                          "SourceRef": {
                            "Entity": "PlanCompteAEF"
                          }
                        },
                        "Property": "DetailNiv2_1"
                      }
                    },
                    "Right": {
                      "Literal": {
                        "Value": "'Clients et comptes rattachés'"
                      }
                    }
                  }
                }
              }
            ]
          }
        },
        {
          "properties": {
            "value": {
              "expr": {
                "Literal": {
                  "Value": "198D"
                }
              }
            }
          },
          "selector": {
            "data": [
              {
                "scopeId": {
                  "Comparison": {
                    "ComparisonKind": 0,
                    "Left": {
                      "Column": {
                        "Expression": {
                          "SourceRef": {
                            "Entity": "PlanCompteAEF"
                          }
                        },
                        "Property": "DetailNiv2_1"
                      }
                    },
                    "Right": {
                      "Literal": {
                        "Value": "'Trésorerie et équivalents de trésorerie'"
                      }
                    }
                  }
                }
              }
            ]
          }
        },
        {
          "properties": {
            "value": {
              "expr": {
                "Literal": {
                  "Value": "168D"
                }
              }
            }
          },
          "selector": {
            "data": [
              {
                "scopeId": {
                  "Comparison": {
                    "ComparisonKind": 0,
                    "Left": {
                      "Column": {
                        "Expression": {
                          "SourceRef": {
                            "Entity": "PlanCompteAEF"
                          }
                        },
                        "Property": "DetailNiv2_1"
                      }
                    },
                    "Right": {
                      "Literal": {
                        "Value": "'Dettes auprès des ets. de crédit'"
                      }
                    }
                  }
                }
              }
            ]
          }
        },
        {
          "properties": {
            "value": {
              "expr": {
                "Literal": {
                  "Value": "109D"
                }
              }
            }
          },
          "selector": {
            "data": [
              {
                "scopeId": {
                  "Comparison": {
                    "ComparisonKind": 0,
                    "Left": {
                      "Column": {
                        "Expression": {
                          "SourceRef": {
                            "Entity": "PlanCompteAEF"
                          }
                        },
                        "Property": "DetailNiv2_1"
                      }
                    },
                    "Right": {
                      "Literal": {
                        "Value": "' Dettes fournisseurs'"
                      }
                    }
                  }
                }
              }
            ]
          }
        },
        {
          "properties": {
            "value": {
              "expr": {
                "Literal": {
                  "Value": "139D"
                }
              }
            }
          },
          "selector": {
            "data": [
              {
                "scopeId": {
                  "Comparison": {
                    "ComparisonKind": 0,
                    "Left": {
                      "Column": {
                        "Expression": {
                          "SourceRef": {
                            "Entity": "PlanCompteAEF"
                          }
                        },
                        "Property": "DetailNiv2_1"
                      }
                    },
                    "Right": {
                      "Literal": {
                        "Value": "' Dettes fiscales et sociales'"
                      }
                    }
                  }
                }
              }
            ]
          }
        },
        {
          "properties": {
            "value": {
              "expr": {
                "Literal": {
                  "Value": "141D"
                }
              }
            }
          },
          "selector": {
            "data": [
              {
                "scopeId": {
                  "Comparison": {
                    "ComparisonKind": 0,
                    "Left": {
                      "Column": {
                        "Expression": {
                          "SourceRef": {
                            "Entity": "PlanCompteAEF"
                          }
                        },
                        "Property": "DetailNiv2_1"
                      }
                    },
                    "Right": {
                      "Literal": {
                        "Value": "'Autres dettes et emprunts'"
                      }
                    }
                  }
                }
              }
            ]
          }
        },
        {
          "properties": {
            "value": {
              "expr": {
                "Literal": {
                  "Value": "158D"
                }
              }
            }
          },
          "selector": {
            "data": [
              {
                "scopeId": {
                  "Comparison": {
                    "ComparisonKind": 0,
                    "Left": {
                      "Column": {
                        "Expression": {
                          "SourceRef": {
                            "Entity": "PlanCompteAEF"
                          }
                        },
                        "Property": "DetailNiv2_1"
                      }
                    },
                    "Right": {
                      "Literal": {
                        "Value": "'Autres produits d''exploitation'"
                      }
                    }
                  }
                }
              }
            ]
          }
        },
        {
          "properties": {
            "value": {
              "expr": {
                "Literal": {
                  "Value": "123D"
                }
              }
            }
          },
          "selector": {
            "data": [
              {
                "scopeId": {
                  "Comparison": {
                    "ComparisonKind": 0,
                    "Left": {
                      "Column": {
                        "Expression": {
                          "SourceRef": {
                            "Entity": "PlanCompteAEF"
                          }
                        },
                        "Property": "DetailNiv2_1"
                      }
                    },
                    "Right": {
                      "Literal": {
                        "Value": "'Charges d''exploitation'"
                      }
                    }
                  }
                }
              }
            ]
          }
        },
        {
          "properties": {
            "value": {
              "expr": {
                "Literal": {
                  "Value": "102D"
                }
              }
            }
          },
          "selector": {
            "data": [
              {
                "scopeId": {
                  "Comparison": {
                    "ComparisonKind": 0,
                    "Left": {
                      "Column": {
                        "Expression": {
                          "SourceRef": {
                            "Entity": "PlanCompteAEF"
                          }
                        },
                        "Property": "DetailNiv2_1"
                      }
                    },
                    "Right": {
                      "Literal": {
                        "Value": "'Produits financiers'"
                      }
                    }
                  }
                }
              }
            ]
          }
        },
        {
          "properties": {
            "value": {
              "expr": {
                "Literal": {
                  "Value": "108D"
                }
              }
            }
          },
          "selector": {
            "data": [
              {
                "scopeId": {
                  "Comparison": {
                    "ComparisonKind": 0,
                    "Left": {
                      "Column": {
                        "Expression": {
                          "SourceRef": {
                            "Entity": "PlanCompteAEF"
                          }
                        },
                        "Property": "DetailNiv2_1"
                      }
                    },
                    "Right": {
                      "Literal": {
                        "Value": "'Charges financières'"
                      }
                    }
                  }
                }
              }
            ]
          }
        },
        {
          "properties": {
            "value": {
              "expr": {
                "Literal": {
                  "Value": "123D"
                }
              }
            }
          },
          "selector": {
            "data": [
              {
                "scopeId": {
                  "Comparison": {
                    "ComparisonKind": 0,
                    "Left": {
                      "Column": {
                        "Expression": {
                          "SourceRef": {
                            "Entity": "PlanCompteAEF"
                          }
                        },
                        "Property": "DetailNiv2_1"
                      }
                    },
                    "Right": {
                      "Literal": {
                        "Value": "'Produits exceptionnels'"
                      }
                    }
                  }
                }
              }
            ]
          }
        },
        {
          "properties": {
            "value": {
              "expr": {
                "Literal": {
                  "Value": "132D"
                }
              }
            }
          },
          "selector": {
            "data": [
              {
                "scopeId": {
                  "Comparison": {
                    "ComparisonKind": 0,
                    "Left": {
                      "Column": {
                        "Expression": {
                          "SourceRef": {
                            "Entity": "PlanCompteAEF"
                          }
                        },
                        "Property": "DetailNiv2_1"
                      }
                    },
                    "Right": {
                      "Literal": {
                        "Value": "'Charges exceptionnelles'"
                      }
                    }
                  }
                }
              }
            ]
          }
        },
        {
          "properties": {
            "value": {
              "expr": {
                "Literal": {
                  "Value": "70D"
                }
              }
            }
          },
          "selector": {
            "data": [
              {
                "total": [
                  {
                    "Column": {
                      "Expression": {
                        "SourceRef": {
                          "Entity": "PlanCompteAEF"
                        }
                      },
                      "Property": "DetailNiv2_1"
                    }
                  }
                ]
              }
            ]
          }
        },
        {
          "properties": {
            "value": {
              "expr": {
                "Literal": {
                  "Value": "405.4537823962962D"
                }
              }
            }
          },
          "selector": {
            "metadata": "PlanCompteAEF.TFT"
          }
        },
        {
          "properties": {
            "value": {
              "expr": {
                "Literal": {
                  "Value": "136.48741054720574D"
                }
              }
            }
          },
          "selector": {
            "metadata": "KPI.Solde TFT Vecrit."
          }
        },
        {
          "properties": {
            "value": {
              "expr": {
                "Literal": {
                  "Value": "61D"
                }
              }
            }
          }
        },
        {
          "properties": {
            "value": {
              "expr": {
                "Literal": {
                  "Value": "90.48588806721219D"
                }
              }
            }
          },
          "selector": {
            "metadata": "KPI._Solde table KPI N cumulé"
          }
        },
        {
          "properties": {
            "value": {
              "expr": {
                "Literal": {
                  "Value": "79.8926460285558D"
                }
              }
            }
          },
          "selector": {
            "metadata": "KPI._Solde table KPI N-1 cumulé"
          }
        },
        {
          "properties": {
            "value": {
              "expr": {
                "Literal": {
                  "Value": "87.3389993987694D"
                }
              }
            }
          },
          "selector": {
            "metadata": "KPI._variation table KPI cumulé"
          }
        },
        {
          "properties": {
            "value": {
              "expr": {
                "Literal": {
                  "Value": "66.2881746801618D"
                }
              }
            }
          },
          "selector": {
            "metadata": "KPI._variation table KPI cumulé %"
          }
        },
        {
          "properties": {
            "value": {
              "expr": {
                "Literal": {
                  "Value": "216.20903315728845D"
                }
              }
            }
          },
          "selector": {
            "metadata": "PlanCompteAEF.CategorieBFR"
          }
        }
      ],
      "rowTotal": [
        {
          "properties": {
            "fontColor": {
              "solid": {
                "color": {
                  "expr": {
                    "ThemeDataColor": {
                      "ColorId": 7,
                      "Percent": 0
                    }
                  }
                }
              }
            },
            "fontFamily": {
              "expr": {
                "Literal": {
                  "Value": "'wf_standard-font, helvetica, arial, sans-serif'"
                }
              }
            },
            "fontSize": {
              "expr": {
                "Literal": {
                  "Value": "8D"
                }
              }
            },
            "bold": {
              "expr": {
                "Literal": {
                  "Value": "true"
                }
              }
            },
            "backColor": {
              "solid": {
                "color": {
                  "expr": {
                    "ThemeDataColor": {
                      "ColorId": 2,
                      "Percent": 0
                    }
                  }
                }
              }
            }
          }
        }
      ],
      "blankRows": [
        {
          "properties": {
            "showBlankRows": {
              "expr": {
                "Literal": {
                  "Value": "false"
                }
              }
            }
          }
        }
      ]
    },
    "visualContainerObjects": {
      "border": [
        {
          "properties": {
            "show": {
              "expr": {
                "Literal": {
                  "Value": "false"
                }
              }
            },
            "color": {
              "solid": {
                "color": {
                  "expr": {
                    "Literal": {
                      "Value": "'#FCFCFC'"
                    }
                  }
                }
              }
            },
            "radius": {
              "expr": {
                "Literal": {
                  "Value": "5D"
                }
              }
            }
          }
        }
      ],
      "stylePreset": [
        {
          "properties": {
            "name": {
              "expr": {
                "Literal": {
                  "Value": "'Minimal'"
                }
              }
            }
          }
        }
      ],
      "lockAspect": [
        {
          "properties": {
            "show": {
              "expr": {
                "Literal": {
                  "Value": "true"
                }
              }
            }
          }
        }
      ],
      "background": [
        {
          "properties": {
            "show": {
              "expr": {
                "Literal": {
                  "Value": "false"
                }
              }
            },
            "transparency": {
              "expr": {
                "Literal": {
                  "Value": "0D"
                }
              }
            }
          }
        }
      ],
      "visualHeader": [
        {
          "properties": {
            "transparency": {
              "expr": {
                "Literal": {
                  "Value": "0D"
                }
              }
            },
            "showFilterRestatementButton": {
              "expr": {
                "Literal": {
                  "Value": "true"
                }
              }
            }
          }
        }
      ],
      "padding": [
        {
          "properties": {
            "top": {
              "expr": {
                "Literal": {
                  "Value": "10D"
                }
              }
            },
            "left": {
              "expr": {
                "Literal": {
                  "Value": "10D"
                }
              }
            },
            "right": {
              "expr": {
                "Literal": {
                  "Value": "10D"
                }
              }
            }
          }
        }
      ],
      "dropShadow": [
        {
          "properties": {
            "show": {
              "expr": {
                "Literal": {
                  "Value": "false"
                }
              }
            }
          }
        }
      ],
      "title": [
        {
          "properties": {
            "show": {
              "expr": {
                "Literal": {
                  "Value": "false"
                }
              }
            },
            "fontColor": {
              "solid": {
                "color": {
                  "expr": {
                    "ThemeDataColor": {
                      "ColorId": 1,
                      "Percent": 0
                    }
                  }
                }
              }
            },
            "fontSize": {
              "expr": {
                "Literal": {
                  "Value": "11D"
                }
              }
            },
            "bold": {
              "expr": {
                "Literal": {
                  "Value": "true"
                }
              }
            },
            "fontFamily": {
              "expr": {
                "Literal": {
                  "Value": "'wf_standard-font_light, helvetica, arial, sans-serif'"
                }
              }
            }
          }
        }
      ],
      "subTitle": [
        {
          "properties": {
            "show": {
              "expr": {
                "Literal": {
                  "Value": "false"
                }
              }
            }
          }
        }
      ],
      "spacing": [
        {
          "properties": {
            "verticalSpacing": {
              "expr": {
                "Literal": {
                  "Value": "10D"
                }
              }
            }
          }
        }
      ]
    },
    "drillFilterOtherVisuals": true
  },
  "filterConfig": {
    "filters": [
      {
        "name": "Filter141dd5e537e49bb2b616",
        "field": {
          "Column": {
            "Expression": {
              "SourceRef": {
                "Entity": "MappingKPI"
              }
            },
            "Property": "Attribute"
          }
        },
        "howCreated": "User"
      },
      {
        "name": "Filtera421d06a61ea8000309d",
        "field": {
          "Column": {
            "Expression": {
              "SourceRef": {
                "Entity": "PlanCompteAEF"
              }
            },
            "Property": "MarquageBFR"
          }
        },
        "filter": {
          "Version": 2,
          "From": [
            {
              "Name": "p",
              "Entity": "PlanCompteAEF",
              "Type": 0
            }
          ],
          "Where": [
            {
              "Condition": {
                "In": {
                  "Expressions": [
                    {
                      "Column": {
                        "Expression": {
                          "SourceRef": {
                            "Source": "p"
                          }
                        },
                        "Property": "MarquageBFR"
                      }
                    }
                  ],
                  "Values": [
                    [
                      {
                        "Literal": {
                          "Value": "'Besoin en fonds de roulement'"
                        }
                      }
                    ]
                  ]
                }
              }
            }
          ]
        },
        "howCreated": "User"
      }
    ]
  }
}